tabular_automl/__init__.py
tabular_automl/settings.py
tabular_automl/tabular_automl.py
tabular_automl/tests.py
tabular_automl-0.1.0.dist-info/LICENSE
tabular_automl-0.1.0.dist-info/METADATA
tabular_automl-0.1.0.dist-info/WHEEL
tabular_automl-0.1.0.dist-info/top_level.txt
tabular_automl-0.1.0.dist-info/RECORD
